Workbook

Sheet README
A1: BLU Use-of-Funds Model - README
A3: How to Use This Model
A5: 1. | B5: Start on the 'Assumptions' sheet. All key inputs are here.
A6: 2. | B6: Cells formatted in Blue with a Light Blue Background are inputs. Change these to test different scenarios.
A7: 3. | B7: All other cells contain formulas and will update automatically.
A8: 4. | B8: 'County_League_Model' projects user growth and ARR based on your assumptions.
A9: 5. | B9: 'Tranche_Detail' and 'Cash_Runway' allocate funds and project cash flow.
A10: 6. | B10: 'Unit_Economics' and 'Milestones' track your key performance indicators (KPIs).
A11: 7. | B11: 'Scenarios' and 'Scenarios_Output' provide a high-level summary of Conservative, Base, and Aggressive outcomes.

Sheet Assumptions
A1: Assumptions
A2: Category | B2: Item | C2: Base | D2: Conservative | E2: Aggressive | F2: Notes
A3: Market | B3: Counties Targeted (Year 1) | C3: 5 | D3: 3 | E3: 8 | F3: Initial focus area
A4: Market | B4: Leagues per County (Avg) | C4: 20 | D4: 15 | E4: 25
A5: Market | B5: Umpires per League (Avg) | C5: 15 | D5: 12 | E5: 18
A6: Market | B6: Parents per Umpire (Avg) | C6: 10 | D6: 8 | E6: 12 | F6: Parents of players in games umpired
A7: Market | B7: Coaches per League (Avg) | C7: 8 | D7: 6 | E7: 10
A8: Conversion | B8: Parent App Conversion % | C8: 0.02 | D8: 0.01 | E8: 0.03 | F8: Freemium to Paid ($199/yr)
A9: Conversion | B9: Coach App Conversion % | C9: 0.1 | D9: 0.05 | E9: 0.15 | F9: Freemium to Paid ($199/yr)
A10: Conversion | B10: League/Org Conversion % (Yr 1) | C10: 0.05 | D10: 0.03 | E10: 0.08 | F10: Leagues converting to B2B platform
A11: Pricing | B11: Coach/Parent App (Annual) | C11: 199 | D11: 199 | E11: 249 | F11: Annual subscription
A12: Pricing | B12: Organization Price (Annual Avg) | C12: 5000 | D12: 3500 | E12: 7500 | F12: Per league, custom pricing
A13: Unit Economics | B13: User Lifetime (Years) | C13: 3 | D13: 2.5 | E13: 3.5
A14: Unit Economics | B14: Gross Margin | C14: 0.55 | D14: 0.5 | E14: 0.6 | F14: Revenue minus COGS (Infra, Support)
A15: Unit Economics | B15: Annual Discount Rate | C15: 0.1 | D15: 0.12 | E15: 0.08 | F15: For LTV calculation (optional)
A16: CAC | B16: CAC - Ambassador ($/user) | C16: 30 | D16: 40 | E16: 25 | F16: Paid user (parent/coach)
A17: CAC | B17: CAC - Social/Digital ($/user) | C17: 80 | D17: 100 | E17: 70 | F17: Paid user (parent/coach)
A18: CAC | B18: CAC - Organization ($/league) | C18: 1200 | D18: 1500 | E18: 1000 | F18: League B2B sale
A19: Team | B19: Employer Burden | C19: 0.1 | D19: 0.12 | E19: 0.1 | F19: % on top of base salary (taxes, benefits)
A20: Team | B20: Engineer Salary (Avg) | C20: 120000 | D20: 110000 | E20: 130000
A21: Team | B21: Sales Salary (Avg) | C21: 80000 | D21: 75000 | E21: 85000
A22: Pay Triggers | B22: Founder Pay - Stage 1 (Annual) | C22: 90000 | D22: 90000 | E22: 90000 | F22: Annual Salary per Founder ($7.5k/mo)
A23: Pay Triggers | B23: Founder Pay - Stage 2 (Annual) | C23: 120000 | D23: 120000 | E23: 120000 | F23: Annual Salary per Founder ($10k/mo)
A24: Pay Triggers | B24: Founder Pay - Stage 3 (Annual) | C24: 250000 | D24: 250000 | E24: 250000 | F24: Annual Salary per Founder
A25: Pay Triggers | B25: MRR Trigger - Stage 2 | C25: 10000 | D25: 10000 | E25: 10000 | F25: MRR threshold for Stage 2 pay
A26: Pay Triggers | B26: MRR Trigger - Stage 3 | C26: 50000 | D26: 50000 | E26: 50000 | F26: MRR threshold for Stage 3 pay
A27: Funding | B27: Tranche A | C27: 250000 | D27: 250000 | E27: 250000 | F27: MVP & Pilot
A28: Funding | B28: Tranche B | C28: 750000 | D28: 750000 | E28: 750000 | F28: Product-Market Fit
A29: Funding | B29: Tranche C | C29: 1000000 | D29: 1000000 | E29: 1000000 | F29: Growth

Sheet Summary
A1: Funding Tranche Summary
A2: Tranche | B2: Amount | C2: Duration (Months) | D2: Primary Use | E2: Key Release Milestones
A3: Tranche A | B3: =Assumptions!C30 | C3: 9 | D3: Build Umpire MVP & Launch Pilots | E3: Initial Close
A4: Tranche B | B4: =Assumptions!C31 | C4: 12 | D4: Achieve Product-Market Fit (Coach/Parent App) | E4: Tranche A Milestones Met (5 Leagues, 100 Umpires)
A5: Tranche C | B5: =Assumptions!C32 | C5: 12 | D5: Drive Scalable Growth (Organization Sales) | E5: Tranche B Milestones Met ($15k MRR, 2% Conversion)
A6: Total | B6: =SUM(B3:B5) | C6: =SUM(C3:C5)

Sheet Tranche_Detail
A1: Tranche Detail - Use of Funds
A2: Category | B2: Item | C2: Tranche A | D2: Tranche B | E2: Tranche C | F2: Total
A3: Payroll | B3: Founders (2) | C3: =Assumptions!C22*2*(Summary!C3/12) | D3: =(Assumptions!C23*2*(3/12))+(Assumptions!C24*2*(9/12)) | E3: =Assumptions!C24*2*(Summary!C5/12) | F3: =SUM(C3:E3)
A4: Payroll | B4: Engineers (2) | C4: =Assumptions!C20*2*(1+Assumptions!C19)*(Summary!C3/12) | D4: =Assumptions!C20*2*(1+Assumptions!C19)*(Summary!C4/12) | E4: =Assumptions!C20*2*(1+Assumptions!C19)*(Summary!C5/12) | F4: =SUM(C4:E4)
A5: Payroll | B5: Sales (1 -> 2) | C5: 0 | D5: =Assumptions!C21*1*(1+Assumptions!C19)*(Summary!C4/12) | E5: =Assumptions!C21*2*(1+Assumptions!C19)*(Summary!C5/12) | F5: =SUM(C5:E5)
A6: Payroll | B6: Total Payroll | C6: =SUM(C3:C5) | D6: =SUM(D3:D5) | E6: =SUM(E3:E5) | F6: =SUM(F3:F5)
A7: Sales & Marketing | B7: CAC - Ambassador | C7: 10000 | D7: 50000 | E7: 100000 | F7: =SUM(C7:E7)
A8: Sales & Marketing | B8: CAC - Social/Digital | C8: 20000 | D8: 75000 | E8: 150000 | F8: =SUM(C8:E8)
A9: Sales & Marketing | B9: CAC - Organization | C9: 5000 | D9: 30000 | E9: 60000 | F9: =SUM(C9:E9)
A10: Sales & Marketing | B10: Total S&M | C10: =SUM(C7:C9) | D10: =SUM(D7:D9) | E10: =SUM(E7:E9) | F10: =SUM(F7:F9)
A11: R&D | B11: Software & Services | C11: 15000 | D11: 30000 | E11: 50000 | F11: =SUM(C11:E11)
A12: R&D | B12: Total R&D | C12: =C11 | D12: =D11 | E12: =E11 | F12: =F11
A13: Infra | B13: Hosting & Data | C13: =Infra_Estimates!F6*(Summary!C3/12) | D13: =Infra_Estimates!F6 | E13: =Infra_Estimates!F6*1.5 | F13: =SUM(C13:E13)
A14: Infra | B14: Total Infra | C14: =C13 | D14: =D13 | E14: =E13 | F14: =F13
A15: G&A | B15: Legal & Admin | C15: 20000 | D15: 30000 | E15: 40000 | F15: =SUM(C15:E15)
A16: G&A | B16: Office & Misc | C16: 10000 | D16: 20000 | E16: 30000 | F16: =SUM(C16:E16)
A17: G&A | B17: Total G&A | C17: =SUM(C15:C16) | D17: =SUM(D15:D16) | E17: =SUM(E15:E16) | F17: =SUM(F15:F16)
A19: Total Allocation | C19: =SUM(C6,C10,C12,C14,C17) | D19: =SUM(D6,D10,D12,D14,D17) | E19: =SUM(E6,E10,E12,E14,E17) | F19: =SUM(F6,F10,F12,F14,F17)
A20: Tranche Amount | C20: =Assumptions!C30 | D20: =Assumptions!C31 | E20: =Assumptions!C32 | F20: =SUM(C20:E20)
A21: Surplus / Deficit | C21: =C20-C19 | D21: =D20-D19 | E21: =E20-E19 | F21: =F20-F19

Sheet County_League_Model
A1: County & League Growth Model (Base Scenario)
A2: Metric | B2: Year 1 | C2: Year 2 | D2: Year 3 | E2: Total
A3: Counties Targeted (New) | B3: =Assumptions!C3 | C3: 10 | D3: 20 | E3: =SUM(B3:D3)
A4: New Leagues Acquired | B4: =B3*Assumptions!C4 | C4: =C3*Assumptions!C4 | D4: =D3*Assumptions!C4 | E4: =SUM(B4:D4)
A5: Total Leagues (Cumulative) | B5: =B4 | C5: =B5+C4 | D5: =C5+D4 | E5: =D5
A7: User Base | B7: Year 1 | C7: Year 2 | D7: Year 3 | E7: Total
A8: Total Umpires | B8: =B5*Assumptions!C5 | C8: =C5*Assumptions!C5 | D8: =D5*Assumptions!C5 | E8: =D8
A9: Total Parents (Potential) | B9: =B8*Assumptions!C6 | C9: =C8*Assumptions!C6 | D9: =D8*Assumptions!C6 | E9: =D9
A10: Total Coaches (Potential) | B10: =B5*Assumptions!C7 | C10: =C5*Assumptions!C7 | D10: =D5*Assumptions!C7 | E10: =D10
A12: Paid Conversions (New) | B12: Year 1 | C12: Year 2 | D12: Year 3 | E12: Total
A13: Paid Parents | B13: =B9*Assumptions!C8 | C13: =C9*Assumptions!C8 | D13: =D9*Assumptions!C8 | E13: =SUM(B13:D13)
A14: Paid Coaches | B14: =B10*Assumptions!C9 | C14: =C10*Assumptions!C9 | D14: =D10*Assumptions!C9 | E14: =SUM(B14:D14)
A15: Paid Organizations | B15: =B4*Assumptions!C10 | C15: =(C4*Assumptions!C10) | D15: =(D4*Assumptions!C10) | E15: =SUM(B15:D15)
A17: Annual Recurring Revenue (ARR) | B17: Year 1 | C17: Year 2 | D17: Year 3 | E17: Total
A18: Parent App Revenue | B18: =B13*Assumptions!C11 | C18: =C13*Assumptions!C11 | D18: =D13*Assumptions!C11 | E18: =SUM(B18:D18)
A19: Coach App Revenue | B19: =B14*Assumptions!C11 | C19: =C14*Assumptions!C11 | D19: =D14*Assumptions!C11 | E19: =SUM(B19:D19)
A20: Organization Revenue | B20: =B15*Assumptions!C12 | C20: =C15*Assumptions!C12 | D20: =D15*Assumptions!C12 | E20: =SUM(B20:D20)
A21: Total ARR | B21: =SUM(B18:B20) | C21: =SUM(C18:C20) | D21: =SUM(D18:D20) | E21: =SUM(B21:D21)
A22: Total MRR (Avg Year 3) | D22: =D21/12

Sheet Unit_Economics
A1: Unit Economics (Base Scenario)
A2: Metric | B2: Parent (App) | C2: Coach (App) | D2: Organization (League) | E2: Blended
A3: ARPU (Annual) | B3: =Assumptions!C11 | C3: =Assumptions!C11 | D3: =Assumptions!C12 | E3: =County_League_Model!D21 / (County_League_Model!D13 + County_League_Model!D14 + County_League_Model!D15)
A4: Gross Margin | B4: =Assumptions!C15 | C4: =Assumptions!C15 | D4: =Assumptions!C15 | E4: =Assumptions!C15
A5: Contribution Margin (Annual) | B5: =B3*B4 | C5: =C3*C4 | D5: =D3*D4 | E5: =E3*E4
A6: Lifetime (Years) | B6: =Assumptions!C14 | C6: =Assumptions!C14 | D6: =Assumptions!C14 | E6: =Assumptions!C14
A7: LTV | B7: =B5*B6 | C7: =C5*C6 | D7: =D5*D6 | E7: =E5*E6
A9: CAC | B9: =Assumptions!C18 | C9: =Assumptions!C18 | D9: =Assumptions!C19 | E9: N/A
A10: LTV / CAC Ratio | B10: =B7/B9 | C10: =C7/C9 | D10: =D7/D9 | E10: N/A
A11: Payback Period (Months) | B11: =(B9/B5)*12 | C11: =(C9/C5)*12 | D11: =(D9/D5)*12 | E11: N/A

Sheet Cash_Runway
A1: Monthly Cash Runway
A2: Month | B2: Opening Cash | C2: Financing | D2: Revenue | E2: Total Cash In | F2: Payroll | G2: S&M | H2: R&D | I2: Infra | J2: G&A | K2: Total Cash Out | L2: Net Burn | M2: Closing Cash | N2: Runway (Months)
A3: 1 | B3: 0 | C3: =Assumptions!C30 | D3: 0 | E3: =C3+D3 | F3: =(Tranche_Detail!C6) / Summary!C3 | G3: =(Tranche_Detail!C10) / Summary!C3 | H3: =(Tranche_Detail!C12) / Summary!C3 | I3: =(Tranche_Detail!C14) / Summary!C3 | J3: =(Tranche_Detail!C17) / Summary!C3 | K3: =SUM(F3:J3) | L3: =K3-D3 | M3: =B3+E3-K3 | N3: =IF(L3>0, M3/L3, 999) | O3: Tranche A Monthly Burn | P3: =(Tranche_Detail!C19) / Summary!C3
A4: 2 | B4: =M3 | C4: 0 | D4: =IF(A4<=12, (County_League_Model!B21/12)*(A4/12), IF(A4<=24, (County_League_Model!C21/12), (County_League_Model!D21/12))) | E4: =C4+D4 | F4: =IF(A4<=Summary!C3, (Tranche_Detail!C6)/Summary!C3, IF(A4<=(Summary!C3+Summary!C4), (Tranche_Detail!D6)/Summary!C4, (Tranche_Detail!E6)/Summary!C5)) | G4: =IF(A4<=Summary!C3, (Tranche_Detail!C10)/Summary!C3, IF(A4<=(Summary!C3+Summary!C4), (Tranche_Detail!D10)/Summary!C4, (Tranche_Detail!E10)/Summary!C5)) | H4: =IF(A4<=Summary!C3, (Tranche_Detail!C12)/Summary!C3, IF(A4<=(Summary!C3+Summary!C4), (Tranche_Detail!D12)/Summary!C4, (Tranche_Detail!E12)/Summary!C5)) | I4: =IF(A4<=Summary!C3, (Tranche_Detail!C14)/Summary!C3, IF(A4<=(Summary!C3+Summary!C4), (Tranche_Detail!D14)/Summary!C4, (Tranche_Detail!E14)/Summary!C5)) | J4: =IF(A4<=Summary!C3, (Tranche_Detail!C17)/Summary!C3, IF(A4<=(Summary!C3+Summary!C4), (Tranche_Detail!D17)/Summary!C4, (Tranche_Detail!E17)/Summary!C5)) | K4: =SUM(F4:J4) | L4: =K4-D4 | M4: =B4+E4-K4 | N4: =IF(L4>0, M4/L4, 999) | O4: Tranche B Monthly Burn | P4: =(Tranche_Detail!D19) / Summary!C4
A5: 3 | B5: =M4 | C5: 0 | D5: =IF(A5<=12, (County_League_Model!B21/12)*(A5/12), IF(A5<=24, (County_League_Model!C21/12), (County_League_Model!D21/12))) | E5: =C5+D5 | F5: =IF(A5<=Summary!C3, (Tranche_Detail!C6)/Summary!C3, IF(A5<=(Summary!C3+Summary!C4), (Tranche_Detail!D6)/Summary!C4, (Tranche_Detail!E6)/Summary!C5)) | G5: =IF(A5<=Summary!C3, (Tranche_Detail!C10)/Summary!C3, IF(A5<=(Summary!C3+Summary!C4), (Tranche_Detail!D10)/Summary!C4, (Tranche_Detail!E10)/Summary!C5)) | H5: =IF(A5<=Summary!C3, (Tranche_Detail!C12)/Summary!C3, IF(A5<=(Summary!C3+Summary!C4), (Tranche_Detail!D12)/Summary!C4, (Tranche_Detail!E12)/Summary!C5)) | I5: =IF(A5<=Summary!C3, (Tranche_Detail!C14)/Summary!C3, IF(A5<=(Summary!C3+Summary!C4), (Tranche_Detail!D14)/Summary!C4, (Tranche_Detail!E14)/Summary!C5)) | J5: =IF(A5<=Summary!C3, (Tranche_Detail!C17)/Summary!C3, IF(A5<=(Summary!C3+Summary!C4), (Tranche_Detail!D17)/Summary!C4, (Tranche_Detail!E17)/Summary!C5)) | K5: =SUM(F5:J5) | L5: =K5-D5 | M5: =B5+E5-K5 | N5: =IF(L5>0, M5/L5, 999) | O5: Tranche C Monthly Burn | P5: =(Tranche_Detail!E19) / Summary!C5
A6: 4 | B6: =M5 | C6: 0 | D6: =IF(A6<=12, (County_League_Model!B21/12)*(A6/12), IF(A6<=24, (County_League_Model!C21/12), (County_League_Model!D21/12))) | E6: =C6+D6 | F6: =IF(A6<=Summary!C3, (Tranche_Detail!C6)/Summary!C3, IF(A6<=(Summary!C3+Summary!C4), (Tranche_Detail!D6)/Summary!C4, (Tranche_Detail!E6)/Summary!C5)) | G6: =IF(A6<=Summary!C3, (Tranche_Detail!C10)/Summary!C3, IF(A6<=(Summary!C3+Summary!C4), (Tranche_Detail!D10)/Summary!C4, (Tranche_Detail!E10)/Summary!C5)) | H6: =IF(A6<=Summary!C3, (Tranche_Detail!C12)/Summary!C3, IF(A6<=(Summary!C3+Summary!C4), (Tranche_Detail!D12)/Summary!C4, (Tranche_Detail!E12)/Summary!C5)) | I6: =IF(A6<=Summary!C3, (Tranche_Detail!C14)/Summary!C3, IF(A6<=(Summary!C3+Summary!C4), (Tranche_Detail!D14)/Summary!C4, (Tranche_Detail!E14)/Summary!C5)) | J6: =IF(A6<=Summary!C3, (Tranche_Detail!C17)/Summary!C3, IF(A6<=(Summary!C3+Summary!C4), (Tranche_Detail!D17)/Summary!C4, (Tranche_Detail!E17)/Summary!C5)) | K6: =SUM(F6:J6) | L6: =K6-D6 | M6: =B6+E6-K6 | N6: =IF(L6>0, M6/L6, 999)
A7: 5 | B7: =M6 | C7: 0 | D7: =IF(A7<=12, (County_League_Model!B21/12)*(A7/12), IF(A7<=24, (County_League_Model!C21/12), (County_League_Model!D21/12))) | E7: =C7+D7 | F7: =IF(A7<=Summary!C3, (Tranche_Detail!C6)/Summary!C3, IF(A7<=(Summary!C3+Summary!C4), (Tranche_Detail!D6)/Summary!C4, (Tranche_Detail!E6)/Summary!C5)) | G7: =IF(A7<=Summary!C3, (Tranche_Detail!C10)/Summary!C3, IF(A7<=(Summary!C3+Summary!C4), (Tranche_Detail!D10)/Summary!C4, (Tranche_Detail!E10)/Summary!C5)) | H7: =IF(A7<=Summary!C3, (Tranche_Detail!C12)/Summary!C3, IF(A7<=(Summary!C3+Summary!C4), (Tranche_Detail!D12)/Summary!C4, (Tranche_Detail!E12)/Summary!C5)) | I7: =IF(A7<=Summary!C3, (Tranche_Detail!C14)/Summary!C3, IF(A7<=(Summary!C3+Summary!C4), (Tranche_Detail!D14)/Summary!C4, (Tranche_Detail!E14)/Summary!C5)) | J7: =IF(A7<=Summary!C3, (Tranche_Detail!C17)/Summary!C3, IF(A7<=(Summary!C3+Summary!C4), (Tranche_Detail!D17)/Summary!C4, (Tranche_Detail!E17)/Summary!C5)) | K7: =SUM(F7:J7) | L7: =K7-D7 | M7: =B7+E7-K7 | N7: =IF(L7>0, M7/L7, 999) | O7: Tranche A Monthly Payroll | P7: =(Tranche_Detail!C6) / Summary!C3
A8: 6 | B8: =M7 | C8: 0 | D8: =IF(A8<=12, (County_League_Model!B21/12)*(A8/12), IF(A8<=24, (County_League_Model!C21/12), (County_League_Model!D21/12))) | E8: =C8+D8 | F8: =IF(A8<=Summary!C3, (Tranche_Detail!C6)/Summary!C3, IF(A8<=(Summary!C3+Summary!C4), (Tranche_Detail!D6)/Summary!C4, (Tranche_Detail!E6)/Summary!C5)) | G8: =IF(A8<=Summary!C3, (Tranche_Detail!C10)/Summary!C3, IF(A8<=(Summary!C3+Summary!C4), (Tranche_Detail!D10)/Summary!C4, (Tranche_Detail!E10)/Summary!C5)) | H8: =IF(A8<=Summary!C3, (Tranche_Detail!C12)/Summary!C3, IF(A8<=(Summary!C3+Summary!C4), (Tranche_Detail!D12)/Summary!C4, (Tranche_Detail!E12)/Summary!C5)) | I8: =IF(A8<=Summary!C3, (Tranche_Detail!C14)/Summary!C3, IF(A8<=(Summary!C3+Summary!C4), (Tranche_Detail!D14)/Summary!C4, (Tranche_Detail!E14)/Summary!C5)) | J8: =IF(A8<=Summary!C3, (Tranche_Detail!C17)/Summary!C3, IF(A8<=(Summary!C3+Summary!C4), (Tranche_Detail!D17)/Summary!C4, (Tranche_Detail!E17)/Summary!C5)) | K8: =SUM(F8:J8) | L8: =K8-D8 | M8: =B8+E8-K8 | N8: =IF(L8>0, M8/L8, 999) | O8: Tranche A Monthly S&M | P8: =(Tranche_Detail!C10) / Summary!C3
A9: 7 | B9: =M8 | C9: 0 | D9: =IF(A9<=12, (County_League_Model!B21/12)*(A9/12), IF(A9<=24, (County_League_Model!C21/12), (County_League_Model!D21/12))) | E9: =C9+D9 | F9: =IF(A9<=Summary!C3, (Tranche_Detail!C6)/Summary!C3, IF(A9<=(Summary!C3+Summary!C4), (Tranche_Detail!D6)/Summary!C4, (Tranche_Detail!E6)/Summary!C5)) | G9: =IF(A9<=Summary!C3, (Tranche_Detail!C10)/Summary!C3, IF(A9<=(Summary!C3+Summary!C4), (Tranche_Detail!D10)/Summary!C4, (Tranche_Detail!E10)/Summary!C5)) | H9: =IF(A9<=Summary!C3, (Tranche_Detail!C12)/Summary!C3, IF(A9<=(Summary!C3+Summary!C4), (Tranche_Detail!D12)/Summary!C4, (Tranche_Detail!E12)/Summary!C5)) | I9: =IF(A9<=Summary!C3, (Tranche_Detail!C14)/Summary!C3, IF(A9<=(Summary!C3+Summary!C4), (Tranche_Detail!D14)/Summary!C4, (Tranche_Detail!E14)/Summary!C5)) | J9: =IF(A9<=Summary!C3, (Tranche_Detail!C17)/Summary!C3, IF(A9<=(Summary!C3+Summary!C4), (Tranche_Detail!D17)/Summary!C4, (Tranche_Detail!E17)/Summary!C5)) | K9: =SUM(F9:J9) | L9: =K9-D9 | M9: =B9+E9-K9 | N9: =IF(L9>0, M9/L9, 999)
A10: 8 | B10: =M9 | C10: 0 | D10: =IF(A10<=12, (County_League_Model!B21/12)*(A10/12), IF(A10<=24, (County_League_Model!C21/12), (County_League_Model!D21/12))) | E10: =C10+D10 | F10: =IF(A10<=Summary!C3, (Tranche_Detail!C6)/Summary!C3, IF(A10<=(Summary!C3+Summary!C4), (Tranche_Detail!D6)/Summary!C4, (Tranche_Detail!E6)/Summary!C5)) | G10: =IF(A10<=Summary!C3, (Tranche_Detail!C10)/Summary!C3, IF(A10<=(Summary!C3+Summary!C4), (Tranche_Detail!D10)/Summary!C4, (Tranche_Detail!E10)/Summary!C5)) | H10: =IF(A10<=Summary!C3, (Tranche_Detail!C12)/Summary!C3, IF(A10<=(Summary!C3+Summary!C4), (Tranche_Detail!D12)/Summary!C4, (Tranche_Detail!E12)/Summary!C5)) | I10: =IF(A10<=Summary!C3, (Tranche_Detail!C14)/Summary!C3, IF(A10<=(Summary!C3+Summary!C4), (Tranche_Detail!D14)/Summary!C4, (Tranche_Detail!E14)/Summary!C5)) | J10: =IF(A10<=Summary!C3, (Tranche_Detail!C17)/Summary!C3, IF(A10<=(Summary!C3+Summary!C4), (Tranche_Detail!D17)/Summary!C4, (Tranche_Detail!E17)/Summary!C5)) | K10: =SUM(F10:J10) | L10: =K10-D10 | M10: =B10+E10-K10 | N10: =IF(L10>0, M10/L10, 999)
A11: 9 | B11: =M10 | C11: 0 | D11: =IF(A11<=12, (County_League_Model!B21/12)*(A11/12), IF(A11<=24, (County_League_Model!C21/12), (County_League_Model!D21/12))) | E11: =C11+D11 | F11: =IF(A11<=Summary!C3, (Tranche_Detail!C6)/Summary!C3, IF(A11<=(Summary!C3+Summary!C4), (Tranche_Detail!D6)/Summary!C4, (Tranche_Detail!E6)/Summary!C5)) | G11: =IF(A11<=Summary!C3, (Tranche_Detail!C10)/Summary!C3, IF(A11<=(Summary!C3+Summary!C4), (Tranche_Detail!D10)/Summary!C4, (Tranche_Detail!E10)/Summary!C5)) | H11: =IF(A11<=Summary!C3, (Tranche_Detail!C12)/Summary!C3, IF(A11<=(Summary!C3+Summary!C4), (Tranche_Detail!D12)/Summary!C4, (Tranche_Detail!E12)/Summary!C5)) | I11: =IF(A11<=Summary!C3, (Tranche_Detail!C14)/Summary!C3, IF(A11<=(Summary!C3+Summary!C4), (Tranche_Detail!D14)/Summary!C4, (Tranche_Detail!E14)/Summary!C5)) | J11: =IF(A11<=Summary!C3, (Tranche_Detail!C17)/Summary!C3, IF(A11<=(Summary!C3+Summary!C4), (Tranche_Detail!D17)/Summary!C4, (Tranche_Detail!E17)/Summary!C5)) | K11: =SUM(F11:J11) | L11: =K11-D11 | M11: =B11+E11-K11 | N11: =IF(L11>0, M11/L11, 999)
A12: 10 | B12: =M11 | C12: =Assumptions!C31 | D12: =IF(A12<=12, (County_League_Model!B21/12)*(A12/12), IF(A12<=24, (County_League_Model!C21/12), (County_League_Model!D21/12))) | E12: =C12+D12 | F12: =IF(A12<=Summary!C3, (Tranche_Detail!C6)/Summary!C3, IF(A12<=(Summary!C3+Summary!C4), (Tranche_Detail!D6)/Summary!C4, (Tranche_Detail!E6)/Summary!C5)) | G12: =IF(A12<=Summary!C3, (Tranche_Detail!C10)/Summary!C3, IF(A12<=(Summary!C3+Summary!C4), (Tranche_Detail!D10)/Summary!C4, (Tranche_Detail!E10)/Summary!C5)) | H12: =IF(A12<=Summary!C3, (Tranche_Detail!C12)/Summary!C3, IF(A12<=(Summary!C3+Summary!C4), (Tranche_Detail!D12)/Summary!C4, (Tranche_Detail!E12)/Summary!C5)) | I12: =IF(A12<=Summary!C3, (Tranche_Detail!C14)/Summary!C3, IF(A12<=(Summary!C3+Summary!C4), (Tranche_Detail!D14)/Summary!C4, (Tranche_Detail!E14)/Summary!C5)) | J12: =IF(A12<=Summary!C3, (Tranche_Detail!C17)/Summary!C3, IF(A12<=(Summary!C3+Summary!C4), (Tranche_Detail!D17)/Summary!C4, (Tranche_Detail!E17)/Summary!C5)) | K12: =SUM(F12:J12) | L12: =K12-D12 | M12: =B12+E12-K12 | N12: =IF(L12>0, M12/L12, 999)
A13: 11 | B13: =M12 | C13: 0 | D13: =IF(A13<=12, (County_League_Model!B21/12)*(A13/12), IF(A13<=24, (County_League_Model!C21/12), (County_League_Model!D21/12))) | E13: =C13+D13 | F13: =IF(A13<=Summary!C3, (Tranche_Detail!C6)/Summary!C3, IF(A13<=(Summary!C3+Summary!C4), (Tranche_Detail!D6)/Summary!C4, (Tranche_Detail!E6)/Summary!C5)) | G13: =IF(A13<=Summary!C3, (Tranche_Detail!C10)/Summary!C3, IF(A13<=(Summary!C3+Summary!C4), (Tranche_Detail!D10)/Summary!C4, (Tranche_Detail!E10)/Summary!C5)) | H13: =IF(A13<=Summary!C3, (Tranche_Detail!C12)/Summary!C3, IF(A13<=(Summary!C3+Summary!C4), (Tranche_Detail!D12)/Summary!C4, (Tranche_Detail!E12)/Summary!C5)) | I13: =IF(A13<=Summary!C3, (Tranche_Detail!C14)/Summary!C3, IF(A13<=(Summary!C3+Summary!C4), (Tranche_Detail!D14)/Summary!C4, (Tranche_Detail!E14)/Summary!C5)) | J13: =IF(A13<=Summary!C3, (Tranche_Detail!C17)/Summary!C3, IF(A13<=(Summary!C3+Summary!C4), (Tranche_Detail!D17)/Summary!C4, (Tranche_Detail!E17)/Summary!C5)) | K13: =SUM(F13:J13) | L13: =K13-D13 | M13: =B13+E13-K13 | N13: =IF(L13>0, M13/L13, 999)
A14: 12 | B14: =M13 | C14: 0 | D14: =IF(A14<=12, (County_League_Model!B21/12)*(A14/12), IF(A14<=24, (County_League_Model!C21/12), (County_League_Model!D21/12))) | E14: =C14+D14 | F14: =IF(A14<=Summary!C3, (Tranche_Detail!C6)/Summary!C3, IF(A14<=(Summary!C3+Summary!C4), (Tranche_Detail!D6)/Summary!C4, (Tranche_Detail!E6)/Summary!C5)) | G14: =IF(A14<=Summary!C3, (Tranche_Detail!C10)/Summary!C3, IF(A14<=(Summary!C3+Summary!C4), (Tranche_Detail!D10)/Summary!C4, (Tranche_Detail!E10)/Summary!C5)) | H14: =IF(A14<=Summary!C3, (Tranche_Detail!C12)/Summary!C3, IF(A14<=(Summary!C3+Summary!C4), (Tranche_Detail!D12)/Summary!C4, (Tranche_Detail!E12)/Summary!C5)) | I14: =IF(A14<=Summary!C3, (Tranche_Detail!C14)/Summary!C3, IF(A14<=(Summary!C3+Summary!C4), (Tranche_Detail!D14)/Summary!C4, (Tranche_Detail!E14)/Summary!C5)) | J14: =IF(A14<=Summary!C3, (Tranche_Detail!C17)/Summary!C3, IF(A14<=(Summary!C3+Summary!C4), (Tranche_Detail!D17)/Summary!C4, (Tranche_Detail!E17)/Summary!C5)) | K14: =SUM(F14:J14) | L14: =K14-D14 | M14: =B14+E14-K14 | N14: =IF(L14>0, M14/L14, 999)
A15: 13 | B15: =M14 | C15: 0 | D15: =IF(A15<=12, (County_League_Model!B21/12)*(A15/12), IF(A15<=24, (County_League_Model!C21/12), (County_League_Model!D21/12))) | E15: =C15+D15 | F15: =IF(A15<=Summary!C3, (Tranche_Detail!C6)/Summary!C3, IF(A15<=(Summary!C3+Summary!C4), (Tranche_Detail!D6)/Summary!C4, (Tranche_Detail!E6)/Summary!C5)) | G15: =IF(A15<=Summary!C3, (Tranche_Detail!C10)/Summary!C3, IF(A15<=(Summary!C3+Summary!C4), (Tranche_Detail!D10)/Summary!C4, (Tranche_Detail!E10)/Summary!C5)) | H15: =IF(A15<=Summary!C3, (Tranche_Detail!C12)/Summary!C3, IF(A15<=(Summary!C3+Summary!C4), (Tranche_Detail!D12)/Summary!C4, (Tranche_Detail!E12)/Summary!C5)) | I15: =IF(A15<=Summary!C3, (Tranche_Detail!C14)/Summary!C3, IF(A15<=(Summary!C3+Summary!C4), (Tranche_Detail!D14)/Summary!C4, (Tranche_Detail!E14)/Summary!C5)) | J15: =IF(A15<=Summary!C3, (Tranche_Detail!C17)/Summary!C3, IF(A15<=(Summary!C3+Summary!C4), (Tranche_Detail!D17)/Summary!C4, (Tranche_Detail!E17)/Summary!C5)) | K15: =SUM(F15:J15) | L15: =K15-D15 | M15: =B15+E15-K15 | N15: =IF(L15>0, M15/L15, 999)
A16: 14 | B16: =M15 | C16: 0 | D16: =IF(A16<=12, (County_League_Model!B21/12)*(A16/12), IF(A16<=24, (County_League_Model!C21/12), (County_League_Model!D21/12))) | E16: =C16+D16 | F16: =IF(A16<=Summary!C3, (Tranche_Detail!C6)/Summary!C3, IF(A16<=(Summary!C3+Summary!C4), (Tranche_Detail!D6)/Summary!C4, (Tranche_Detail!E6)/Summary!C5)) | G16: =IF(A16<=Summary!C3, (Tranche_Detail!C10)/Summary!C3, IF(A16<=(Summary!C3+Summary!C4), (Tranche_Detail!D10)/Summary!C4, (Tranche_Detail!E10)/Summary!C5)) | H16: =IF(A16<=Summary!C3, (Tranche_Detail!C12)/Summary!C3, IF(A16<=(Summary!C3+Summary!C4), (Tranche_Detail!D12)/Summary!C4, (Tranche_Detail!E12)/Summary!C5)) | I16: =IF(A16<=Summary!C3, (Tranche_Detail!C14)/Summary!C3, IF(A16<=(Summary!C3+Summary!C4), (Tranche_Detail!D14)/Summary!C4, (Tranche_Detail!E14)/Summary!C5)) | J16: =IF(A16<=Summary!C3, (Tranche_Detail!C17)/Summary!C3, IF(A16<=(Summary!C3+Summary!C4), (Tranche_Detail!D17)/Summary!C4, (Tranche_Detail!E17)/Summary!C5)) | K16: =SUM(F16:J16) | L16: =K16-D16 | M16: =B16+E16-K16 | N16: =IF(L16>0, M16/L16, 999)
A17: 15 | B17: =M16 | C17: 0 | D17: =IF(A17<=12, (County_League_Model!B21/12)*(A17/12), IF(A17<=24, (County_League_Model!C21/12), (County_League_Model!D21/12))) | E17: =C17+D17 | F17: =IF(A17<=Summary!C3, (Tranche_Detail!C6)/Summary!C3, IF(A17<=(Summary!C3+Summary!C4), (Tranche_Detail!D6)/Summary!C4, (Tranche_Detail!E6)/Summary!C5)) | G17: =IF(A17<=Summary!C3, (Tranche_Detail!C10)/Summary!C3, IF(A17<=(Summary!C3+Summary!C4), (Tranche_Detail!D10)/Summary!C4, (Tranche_Detail!E10)/Summary!C5)) | H17: =IF(A17<=Summary!C3, (Tranche_Detail!C12)/Summary!C3, IF(A17<=(Summary!C3+Summary!C4), (Tranche_Detail!D12)/Summary!C4, (Tranche_Detail!E12)/Summary!C5)) | I17: =IF(A17<=Summary!C3, (Tranche_Detail!C14)/Summary!C3, IF(A17<=(Summary!C3+Summary!C4), (Tranche_Detail!D14)/Summary!C4, (Tranche_Detail!E14)/Summary!C5)) | J17: =IF(A17<=Summary!C3, (Tranche_Detail!C17)/Summary!C3, IF(A17<=(Summary!C3+Summary!C4), (Tranche_Detail!D17)/Summary!C4, (Tranche_Detail!E17)/Summary!C5)) | K17: =SUM(F17:J17) | L17: =K17-D17 | M17: =B17+E17-K17 | N17: =IF(L17>0, M17/L17, 999)
A18: 16 | B18: =M17 | C18: 0 | D18: =IF(A18<=12, (County_League_Model!B21/12)*(A18/12), IF(A18<=24, (County_League_Model!C21/12), (County_League_Model!D21/12))) | E18: =C18+D18 | F18: =IF(A18<=Summary!C3, (Tranche_Detail!C6)/Summary!C3, IF(A18<=(Summary!C3+Summary!C4), (Tranche_Detail!D6)/Summary!C4, (Tranche_Detail!E6)/Summary!C5)) | G18: =IF(A18<=Summary!C3, (Tranche_Detail!C10)/Summary!C3, IF(A18<=(Summary!C3+Summary!C4), (Tranche_Detail!D10)/Summary!C4, (Tranche_Detail!E10)/Summary!C5)) | H18: =IF(A18<=Summary!C3, (Tranche_Detail!C12)/Summary!C3, IF(A18<=(Summary!C3+Summary!C4), (Tranche_Detail!D12)/Summary!C4, (Tranche_Detail!E12)/Summary!C5)) | I18: =IF(A18<=Summary!C3, (Tranche_Detail!C14)/Summary!C3, IF(A18<=(Summary!C3+Summary!C4), (Tranche_Detail!D14)/Summary!C4, (Tranche_Detail!E14)/Summary!C5)) | J18: =IF(A18<=Summary!C3, (Tranche_Detail!C17)/Summary!C3, IF(A18<=(Summary!C3+Summary!C4), (Tranche_Detail!D17)/Summary!C4, (Tranche_Detail!E17)/Summary!C5)) | K18: =SUM(F18:J18) | L18: =K18-D18 | M18: =B18+E18-K18 | N18: =IF(L18>0, M18/L18, 999)
A19: 17 | B19: =M18 | C19: 0 | D19: =IF(A19<=12, (County_League_Model!B21/12)*(A19/12), IF(A19<=24, (County_League_Model!C21/12), (County_League_Model!D21/12))) | E19: =C19+D19 | F19: =IF(A19<=Summary!C3, (Tranche_Detail!C6)/Summary!C3, IF(A19<=(Summary!C3+Summary!C4), (Tranche_Detail!D6)/Summary!C4, (Tranche_Detail!E6)/Summary!C5)) | G19: =IF(A19<=Summary!C3, (Tranche_Detail!C10)/Summary!C3, IF(A19<=(Summary!C3+Summary!C4), (Tranche_Detail!D10)/Summary!C4, (Tranche_Detail!E10)/Summary!C5)) | H19: =IF(A19<=Summary!C3, (Tranche_Detail!C12)/Summary!C3, IF(A19<=(Summary!C3+Summary!C4), (Tranche_Detail!D12)/Summary!C4, (Tranche_Detail!E12)/Summary!C5)) | I19: =IF(A19<=Summary!C3, (Tranche_Detail!C14)/Summary!C3, IF(A19<=(Summary!C3+Summary!C4), (Tranche_Detail!D14)/Summary!C4, (Tranche_Detail!E14)/Summary!C5)) | J19: =IF(A19<=Summary!C3, (Tranche_Detail!C17)/Summary!C3, IF(A19<=(Summary!C3+Summary!C4), (Tranche_Detail!D17)/Summary!C4, (Tranche_Detail!E17)/Summary!C5)) | K19: =SUM(F19:J19) | L19: =K19-D19 | M19: =B19+E19-K19 | N19: =IF(L19>0, M19/L19, 999)
A20: 18 | B20: =M19 | C20: 0 | D20: =IF(A20<=12, (County_League_Model!B21/12)*(A20/12), IF(A20<=24, (County_League_Model!C21/12), (County_League_Model!D21/12))) | E20: =C20+D20 | F20: =IF(A20<=Summary!C3, (Tranche_Detail!C6)/Summary!C3, IF(A20<=(Summary!C3+Summary!C4), (Tranche_Detail!D6)/Summary!C4, (Tranche_Detail!E6)/Summary!C5)) | G20: =IF(A20<=Summary!C3, (Tranche_Detail!C10)/Summary!C3, IF(A20<=(Summary!C3+Summary!C4), (Tranche_Detail!D10)/Summary!C4, (Tranche_Detail!E10)/Summary!C5)) | H20: =IF(A20<=Summary!C3, (Tranche_Detail!C12)/Summary!C3, IF(A20<=(Summary!C3+Summary!C4), (Tranche_Detail!D12)/Summary!C4, (Tranche_Detail!E12)/Summary!C5)) | I20: =IF(A20<=Summary!C3, (Tranche_Detail!C14)/Summary!C3, IF(A20<=(Summary!C3+Summary!C4), (Tranche_Detail!D14)/Summary!C4, (Tranche_Detail!E14)/Summary!C5)) | J20: =IF(A20<=Summary!C3, (Tranche_Detail!C17)/Summary!C3, IF(A20<=(Summary!C3+Summary!C4), (Tranche_Detail!D17)/Summary!C4, (Tranche_Detail!E17)/Summary!C5)) | K20: =SUM(F20:J20) | L20: =K20-D20 | M20: =B20+E20-K20 | N20: =IF(L20>0, M20/L20, 999)
A21: 19 | B21: =M20 | C21: 0 | D21: =IF(A21<=12, (County_League_Model!B21/12)*(A21/12), IF(A21<=24, (County_League_Model!C21/12), (County_League_Model!D21/12))) | E21: =C21+D21 | F21: =IF(A21<=Summary!C3, (Tranche_Detail!C6)/Summary!C3, IF(A21<=(Summary!C3+Summary!C4), (Tranche_Detail!D6)/Summary!C4, (Tranche_Detail!E6)/Summary!C5)) | G21: =IF(A21<=Summary!C3, (Tranche_Detail!C10)/Summary!C3, IF(A21<=(Summary!C3+Summary!C4), (Tranche_Detail!D10)/Summary!C4, (Tranche_Detail!E10)/Summary!C5)) | H21: =IF(A21<=Summary!C3, (Tranche_Detail!C12)/Summary!C3, IF(A21<=(Summary!C3+Summary!C4), (Tranche_Detail!D12)/Summary!C4, (Tranche_Detail!E12)/Summary!C5)) | I21: =IF(A21<=Summary!C3, (Tranche_Detail!C14)/Summary!C3, IF(A21<=(Summary!C3+Summary!C4), (Tranche_Detail!D14)/Summary!C4, (Tranche_Detail!E14)/Summary!C5)) | J21: =IF(A21<=Summary!C3, (Tranche_Detail!C17)/Summary!C3, IF(A21<=(Summary!C3+Summary!C4), (Tranche_Detail!D17)/Summary!C4, (Tranche_Detail!E17)/Summary!C5)) | K21: =SUM(F21:J21) | L21: =K21-D21 | M21: =B21+E21-K21 | N21: =IF(L21>0, M21/L21, 999)
A22: 20 | B22: =M21 | C22: 0 | D22: =IF(A22<=12, (County_League_Model!B21/12)*(A22/12), IF(A22<=24, (County_League_Model!C21/12), (County_League_Model!D21/12))) | E22: =C22+D22 | F22: =IF(A22<=Summary!C3, (Tranche_Detail!C6)/Summary!C3, IF(A22<=(Summary!C3+Summary!C4), (Tranche_Detail!D6)/Summary!C4, (Tranche_Detail!E6)/Summary!C5)) | G22: =IF(A22<=Summary!C3, (Tranche_Detail!C10)/Summary!C3, IF(A22<=(Summary!C3+Summary!C4), (Tranche_Detail!D10)/Summary!C4, (Tranche_Detail!E10)/Summary!C5)) | H22: =IF(A22<=Summary!C3, (Tranche_Detail!C12)/Summary!C3, IF(A22<=(Summary!C3+Summary!C4), (Tranche_Detail!D12)/Summary!C4, (Tranche_Detail!E12)/Summary!C5)) | I22: =IF(A22<=Summary!C3, (Tranche_Detail!C14)/Summary!C3, IF(A22<=(Summary!C3+Summary!C4), (Tranche_Detail!D14)/Summary!C4, (Tranche_Detail!E14)/Summary!C5)) | J22: =IF(A22<=Summary!C3, (Tranche_Detail!C17)/Summary!C3, IF(A22<=(Summary!C3+Summary!C4), (Tranche_Detail!D17)/Summary!C4, (Tranche_Detail!E17)/Summary!C5)) | K22: =SUM(F22:J22) | L22: =K22-D22 | M22: =B22+E22-K22 | N22: =IF(L22>0, M22/L22, 999)
A23: 21 | B23: =M22 | C23: 0 | D23: =IF(A23<=12, (County_League_Model!B21/12)*(A23/12), IF(A23<=24, (County_League_Model!C21/12), (County_League_Model!D21/12))) | E23: =C23+D23 | F23: =IF(A23<=Summary!C3, (Tranche_Detail!C6)/Summary!C3, IF(A23<=(Summary!C3+Summary!C4), (Tranche_Detail!D6)/Summary!C4, (Tranche_Detail!E6)/Summary!C5)) | G23: =IF(A23<=Summary!C3, (Tranche_Detail!C10)/Summary!C3, IF(A23<=(Summary!C3+Summary!C4), (Tranche_Detail!D10)/Summary!C4, (Tranche_Detail!E10)/Summary!C5)) | H23: =IF(A23<=Summary!C3, (Tranche_Detail!C12)/Summary!C3, IF(A23<=(Summary!C3+Summary!C4), (Tranche_Detail!D12)/Summary!C4, (Tranche_Detail!E12)/Summary!C5)) | I23: =IF(A23<=Summary!C3, (Tranche_Detail!C14)/Summary!C3, IF(A23<=(Summary!C3+Summary!C4), (Tranche_Detail!D14)/Summary!C4, (Tranche_Detail!E14)/Summary!C5)) | J23: =IF(A23<=Summary!C3, (Tranche_Detail!C17)/Summary!C3, IF(A23<=(Summary!C3+Summary!C4), (Tranche_Detail!D17)/Summary!C4, (Tranche_Detail!E17)/Summary!C5)) | K23: =SUM(F23:J23) | L23: =K23-D23 | M23: =B23+E23-K23 | N23: =IF(L23>0, M23/L23, 999)
A24: 22 | B24: =M23 | C24: =Assumptions!C32 | D24: =IF(A24<=12, (County_League_Model!B21/12)*(A24/12), IF(A24<=24, (County_League_Model!C21/12), (County_League_Model!D21/12))) | E24: =C24+D24 | F24: =IF(A24<=Summary!C3, (Tranche_Detail!C6)/Summary!C3, IF(A24<=(Summary!C3+Summary!C4), (Tranche_Detail!D6)/Summary!C4, (Tranche_Detail!E6)/Summary!C5)) | G24: =IF(A24<=Summary!C3, (Tranche_Detail!C10)/Summary!C3, IF(A24<=(Summary!C3+Summary!C4), (Tranche_Detail!D10)/Summary!C4, (Tranche_Detail!E10)/Summary!C5)) | H24: =IF(A24<=Summary!C3, (Tranche_Detail!C12)/Summary!C3, IF(A24<=(Summary!C3+Summary!C4), (Tranche_Detail!D12)/Summary!C4, (Tranche_Detail!E12)/Summary!C5)) | I24: =IF(A24<=Summary!C3, (Tranche_Detail!C14)/Summary!C3, IF(A24<=(Summary!C3+Summary!C4), (Tranche_Detail!D14)/Summary!C4, (Tranche_Detail!E14)/Summary!C5)) | J24: =IF(A24<=Summary!C3, (Tranche_Detail!C17)/Summary!C3, IF(A24<=(Summary!C3+Summary!C4), (Tranche_Detail!D17)/Summary!C4, (Tranche_Detail!E17)/Summary!C5)) | K24: =SUM(F24:J24) | L24: =K24-D24 | M24: =B24+E24-K24 | N24: =IF(L24>0, M24/L24, 999)
A25: 23 | B25: =M24 | C25: 0 | D25: =IF(A25<=12, (County_League_Model!B21/12)*(A25/12), IF(A25<=24, (County_League_Model!C21/12), (County_League_Model!D21/12))) | E25: =C25+D25 | F25: =IF(A25<=Summary!C3, (Tranche_Detail!C6)/Summary!C3, IF(A25<=(Summary!C3+Summary!C4), (Tranche_Detail!D6)/Summary!C4, (Tranche_Detail!E6)/Summary!C5)) | G25: =IF(A25<=Summary!C3, (Tranche_Detail!C10)/Summary!C3, IF(A25<=(Summary!C3+Summary!C4), (Tranche_Detail!D10)/Summary!C4, (Tranche_Detail!E10)/Summary!C5)) | H25: =IF(A25<=Summary!C3, (Tranche_Detail!C12)/Summary!C3, IF(A25<=(Summary!C3+Summary!C4), (Tranche_Detail!D12)/Summary!C4, (Tranche_Detail!E12)/Summary!C5)) | I25: =IF(A25<=Summary!C3, (Tranche_Detail!C14)/Summary!C3, IF(A25<=(Summary!C3+Summary!C4), (Tranche_Detail!D14)/Summary!C4, (Tranche_Detail!E14)/Summary!C5)) | J25: =IF(A25<=Summary!C3, (Tranche_Detail!C17)/Summary!C3, IF(A25<=(Summary!C3+Summary!C4), (Tranche_Detail!D17)/Summary!C4, (Tranche_Detail!E17)/Summary!C5)) | K25: =SUM(F25:J25) | L25: =K25-D25 | M25: =B25+E25-K25 | N25: =IF(L25>0, M25/L25, 999)
A26: 24 | B26: =M25 | C26: 0 | D26: =IF(A26<=12, (County_League_Model!B21/12)*(A26/12), IF(A26<=24, (County_League_Model!C21/12), (County_League_Model!D21/12))) | E26: =C26+D26 | F26: =IF(A26<=Summary!C3, (Tranche_Detail!C6)/Summary!C3, IF(A26<=(Summary!C3+Summary!C4), (Tranche_Detail!D6)/Summary!C4, (Tranche_Detail!E6)/Summary!C5)) | G26: =IF(A26<=Summary!C3, (Tranche_Detail!C10)/Summary!C3, IF(A26<=(Summary!C3+Summary!C4), (Tranche_Detail!D10)/Summary!C4, (Tranche_Detail!E10)/Summary!C5)) | H26: =IF(A26<=Summary!C3, (Tranche_Detail!C12)/Summary!C3, IF(A26<=(Summary!C3+Summary!C4), (Tranche_Detail!D12)/Summary!C4, (Tranche_Detail!E12)/Summary!C5)) | I26: =IF(A26<=Summary!C3, (Tranche_Detail!C14)/Summary!C3, IF(A26<=(Summary!C3+Summary!C4), (Tranche_Detail!D14)/Summary!C4, (Tranche_Detail!E14)/Summary!C5)) | J26: =IF(A26<=Summary!C3, (Tranche_Detail!C17)/Summary!C3, IF(A26<=(Summary!C3+Summary!C4), (Tranche_Detail!D17)/Summary!C4, (Tranche_Detail!E17)/Summary!C5)) | K26: =SUM(F26:J26) | L26: =K26-D26 | M26: =B26+E26-K26 | N26: =IF(L26>0, M26/L26, 999)
A27: 25 | B27: =M26 | C27: 0 | D27: =IF(A27<=12, (County_League_Model!B21/12)*(A27/12), IF(A27<=24, (County_League_Model!C21/12), (County_League_Model!D21/12))) | E27: =C27+D27 | F27: =IF(A27<=Summary!C3, (Tranche_Detail!C6)/Summary!C3, IF(A27<=(Summary!C3+Summary!C4), (Tranche_Detail!D6)/Summary!C4, (Tranche_Detail!E6)/Summary!C5)) | G27: =IF(A27<=Summary!C3, (Tranche_Detail!C10)/Summary!C3, IF(A27<=(Summary!C3+Summary!C4), (Tranche_Detail!D10)/Summary!C4, (Tranche_Detail!E10)/Summary!C5)) | H27: =IF(A27<=Summary!C3, (Tranche_Detail!C12)/Summary!C3, IF(A27<=(Summary!C3+Summary!C4), (Tranche_Detail!D12)/Summary!C4, (Tranche_Detail!E12)/Summary!C5)) | I27: =IF(A27<=Summary!C3, (Tranche_Detail!C14)/Summary!C3, IF(A27<=(Summary!C3+Summary!C4), (Tranche_Detail!D14)/Summary!C4, (Tranche_Detail!E14)/Summary!C5)) | J27: =IF(A27<=Summary!C3, (Tranche_Detail!C17)/Summary!C3, IF(A27<=(Summary!C3+Summary!C4), (Tranche_Detail!D17)/Summary!C4, (Tranche_Detail!E17)/Summary!C5)) | K27: =SUM(F27:J27) | L27: =K27-D27 | M27: =B27+E27-K27 | N27: =IF(L27>0, M27/L27, 999)
A28: 26 | B28: =M27 | C28: 0 | D28: =IF(A28<=12, (County_League_Model!B21/12)*(A28/12), IF(A28<=24, (County_League_Model!C21/12), (County_League_Model!D21/12))) | E28: =C28+D28 | F28: =IF(A28<=Summary!C3, (Tranche_Detail!C6)/Summary!C3, IF(A28<=(Summary!C3+Summary!C4), (Tranche_Detail!D6)/Summary!C4, (Tranche_Detail!E6)/Summary!C5)) | G28: =IF(A28<=Summary!C3, (Tranche_Detail!C10)/Summary!C3, IF(A28<=(Summary!C3+Summary!C4), (Tranche_Detail!D10)/Summary!C4, (Tranche_Detail!E10)/Summary!C5)) | H28: =IF(A28<=Summary!C3, (Tranche_Detail!C12)/Summary!C3, IF(A28<=(Summary!C3+Summary!C4), (Tranche_Detail!D12)/Summary!C4, (Tranche_Detail!E12)/Summary!C5)) | I28: =IF(A28<=Summary!C3, (Tranche_Detail!C14)/Summary!C3, IF(A28<=(Summary!C3+Summary!C4), (Tranche_Detail!D14)/Summary!C4, (Tranche_Detail!E14)/Summary!C5)) | J28: =IF(A28<=Summary!C3, (Tranche_Detail!C17)/Summary!C3, IF(A28<=(Summary!C3+Summary!C4), (Tranche_Detail!D17)/Summary!C4, (Tranche_Detail!E17)/Summary!C5)) | K28: =SUM(F28:J28) | L28: =K28-D28 | M28: =B28+E28-K28 | N28: =IF(L28>0, M28/L28, 999)
A29: 27 | B29: =M28 | C29: 0 | D29: =IF(A29<=12, (County_League_Model!B21/12)*(A29/12), IF(A29<=24, (County_League_Model!C21/12), (County_League_Model!D21/12))) | E29: =C29+D29 | F29: =IF(A29<=Summary!C3, (Tranche_Detail!C6)/Summary!C3, IF(A29<=(Summary!C3+Summary!C4), (Tranche_Detail!D6)/Summary!C4, (Tranche_Detail!E6)/Summary!C5)) | G29: =IF(A29<=Summary!C3, (Tranche_Detail!C10)/Summary!C3, IF(A29<=(Summary!C3+Summary!C4), (Tranche_Detail!D10)/Summary!C4, (Tranche_Detail!E10)/Summary!C5)) | H29: =IF(A29<=Summary!C3, (Tranche_Detail!C12)/Summary!C3, IF(A29<=(Summary!C3+Summary!C4), (Tranche_Detail!D12)/Summary!C4, (Tranche_Detail!E12)/Summary!C5)) | I29: =IF(A29<=Summary!C3, (Tranche_Detail!C14)/Summary!C3, IF(A29<=(Summary!C3+Summary!C4), (Tranche_Detail!D14)/Summary!C4, (Tranche_Detail!E14)/Summary!C5)) | J29: =IF(A29<=Summary!C3, (Tranche_Detail!C17)/Summary!C3, IF(A29<=(Summary!C3+Summary!C4), (Tranche_Detail!D17)/Summary!C4, (Tranche_Detail!E17)/Summary!C5)) | K29: =SUM(F29:J29) | L29: =K29-D29 | M29: =B29+E29-K29 | N29: =IF(L29>0, M29/L29, 999)
A30: 28 | B30: =M29 | C30: 0 | D30: =IF(A30<=12, (County_League_Model!B21/12)*(A30/12), IF(A30<=24, (County_League_Model!C21/12), (County_League_Model!D21/12))) | E30: =C30+D30 | F30: =IF(A30<=Summary!C3, (Tranche_Detail!C6)/Summary!C3, IF(A30<=(Summary!C3+Summary!C4), (Tranche_Detail!D6)/Summary!C4, (Tranche_Detail!E6)/Summary!C5)) | G30: =IF(A30<=Summary!C3, (Tranche_Detail!C10)/Summary!C3, IF(A30<=(Summary!C3+Summary!C4), (Tranche_Detail!D10)/Summary!C4, (Tranche_Detail!E10)/Summary!C5)) | H30: =IF(A30<=Summary!C3, (Tranche_Detail!C12)/Summary!C3, IF(A30<=(Summary!C3+Summary!C4), (Tranche_Detail!D12)/Summary!C4, (Tranche_Detail!E12)/Summary!C5)) | I30: =IF(A30<=Summary!C3, (Tranche_Detail!C14)/Summary!C3, IF(A30<=(Summary!C3+Summary!C4), (Tranche_Detail!D14)/Summary!C4, (Tranche_Detail!E14)/Summary!C5)) | J30: =IF(A30<=Summary!C3, (Tranche_Detail!C17)/Summary!C3, IF(A30<=(Summary!C3+Summary!C4), (Tranche_Detail!D17)/Summary!C4, (Tranche_Detail!E17)/Summary!C5)) | K30: =SUM(F30:J30) | L30: =K30-D30 | M30: =B30+E30-K30 | N30: =IF(L30>0, M30/L30, 999)
A31: 29 | B31: =M30 | C31: 0 | D31: =IF(A31<=12, (County_League_Model!B21/12)*(A31/12), IF(A31<=24, (County_League_Model!C21/12), (County_League_Model!D21/12))) | E31: =C31+D31 | F31: =IF(A31<=Summary!C3, (Tranche_Detail!C6)/Summary!C3, IF(A31<=(Summary!C3+Summary!C4), (Tranche_Detail!D6)/Summary!C4, (Tranche_Detail!E6)/Summary!C5)) | G31: =IF(A31<=Summary!C3, (Tranche_Detail!C10)/Summary!C3, IF(A31<=(Summary!C3+Summary!C4), (Tranche_Detail!D10)/Summary!C4, (Tranche_Detail!E10)/Summary!C5)) | H31: =IF(A31<=Summary!C3, (Tranche_Detail!C12)/Summary!C3, IF(A31<=(Summary!C3+Summary!C4), (Tranche_Detail!D12)/Summary!C4, (Tranche_Detail!E12)/Summary!C5)) | I31: =IF(A31<=Summary!C3, (Tranche_Detail!C14)/Summary!C3, IF(A31<=(Summary!C3+Summary!C4), (Tranche_Detail!D14)/Summary!C4, (Tranche_Detail!E14)/Summary!C5)) | J31: =IF(A31<=Summary!C3, (Tranche_Detail!C17)/Summary!C3, IF(A31<=(Summary!C3+Summary!C4), (Tranche_Detail!D17)/Summary!C4, (Tranche_Detail!E17)/Summary!C5)) | K31: =SUM(F31:J31) | L31: =K31-D31 | M31: =B31+E31-K31 | N31: =IF(L31>0, M31/L31, 999)
A32: 30 | B32: =M31 | C32: 0 | D32: =IF(A32<=12, (County_League_Model!B21/12)*(A32/12), IF(A32<=24, (County_League_Model!C21/12), (County_League_Model!D21/12))) | E32: =C32+D32 | F32: =IF(A32<=Summary!C3, (Tranche_Detail!C6)/Summary!C3, IF(A32<=(Summary!C3+Summary!C4), (Tranche_Detail!D6)/Summary!C4, (Tranche_Detail!E6)/Summary!C5)) | G32: =IF(A32<=Summary!C3, (Tranche_Detail!C10)/Summary!C3, IF(A32<=(Summary!C3+Summary!C4), (Tranche_Detail!D10)/Summary!C4, (Tranche_Detail!E10)/Summary!C5)) | H32: =IF(A32<=Summary!C3, (Tranche_Detail!C12)/Summary!C3, IF(A32<=(Summary!C3+Summary!C4), (Tranche_Detail!D12)/Summary!C4, (Tranche_Detail!E12)/Summary!C5)) | I32: =IF(A32<=Summary!C3, (Tranche_Detail!C14)/Summary!C3, IF(A32<=(Summary!C3+Summary!C4), (Tranche_Detail!D14)/Summary!C4, (Tranche_Detail!E14)/Summary!C5)) | J32: =IF(A32<=Summary!C3, (Tranche_Detail!C17)/Summary!C3, IF(A32<=(Summary!C3+Summary!C4), (Tranche_Detail!D17)/Summary!C4, (Tranche_Detail!E17)/Summary!C5)) | K32: =SUM(F32:J32) | L32: =K32-D32 | M32: =B32+E32-K32 | N32: =IF(L32>0, M32/L32, 999)
A33: 31 | B33: =M32 | C33: 0 | D33: =IF(A33<=12, (County_League_Model!B21/12)*(A33/12), IF(A33<=24, (County_League_Model!C21/12), (County_League_Model!D21/12))) | E33: =C33+D33 | F33: =IF(A33<=Summary!C3, (Tranche_Detail!C6)/Summary!C3, IF(A33<=(Summary!C3+Summary!C4), (Tranche_Detail!D6)/Summary!C4, (Tranche_Detail!E6)/Summary!C5)) | G33: =IF(A33<=Summary!C3, (Tranche_Detail!C10)/Summary!C3, IF(A33<=(Summary!C3+Summary!C4), (Tranche_Detail!D10)/Summary!C4, (Tranche_Detail!E10)/Summary!C5)) | H33: =IF(A33<=Summary!C3, (Tranche_Detail!C12)/Summary!C3, IF(A33<=(Summary!C3+Summary!C4), (Tranche_Detail!D12)/Summary!C4, (Tranche_Detail!E12)/Summary!C5)) | I33: =IF(A33<=Summary!C3, (Tranche_Detail!C14)/Summary!C3, IF(A33<=(Summary!C3+Summary!C4), (Tranche_Detail!D14)/Summary!C4, (Tranche_Detail!E14)/Summary!C5)) | J33: =IF(A33<=Summary!C3, (Tranche_Detail!C17)/Summary!C3, IF(A33<=(Summary!C3+Summary!C4), (Tranche_Detail!D17)/Summary!C4, (Tranche_Detail!E17)/Summary!C5)) | K33: =SUM(F33:J33) | L33: =K33-D33 | M33: =B33+E33-K33 | N33: =IF(L33>0, M33/L33, 999)
A34: 32 | B34: =M33 | C34: 0 | D34: =IF(A34<=12, (County_League_Model!B21/12)*(A34/12), IF(A34<=24, (County_League_Model!C21/12), (County_League_Model!D21/12))) | E34: =C34+D34 | F34: =IF(A34<=Summary!C3, (Tranche_Detail!C6)/Summary!C3, IF(A34<=(Summary!C3+Summary!C4), (Tranche_Detail!D6)/Summary!C4, (Tranche_Detail!E6)/Summary!C5)) | G34: =IF(A34<=Summary!C3, (Tranche_Detail!C10)/Summary!C3, IF(A34<=(Summary!C3+Summary!C4), (Tranche_Detail!D10)/Summary!C4, (Tranche_Detail!E10)/Summary!C5)) | H34: =IF(A34<=Summary!C3, (Tranche_Detail!C12)/Summary!C3, IF(A34<=(Summary!C3+Summary!C4), (Tranche_Detail!D12)/Summary!C4, (Tranche_Detail!E12)/Summary!C5)) | I34: =IF(A34<=Summary!C3, (Tranche_Detail!C14)/Summary!C3, IF(A34<=(Summary!C3+Summary!C4), (Tranche_Detail!D14)/Summary!C4, (Tranche_Detail!E14)/Summary!C5)) | J34: =IF(A34<=Summary!C3, (Tranche_Detail!C17)/Summary!C3, IF(A34<=(Summary!C3+Summary!C4), (Tranche_Detail!D17)/Summary!C4, (Tranche_Detail!E17)/Summary!C5)) | K34: =SUM(F34:J34) | L34: =K34-D34 | M34: =B34+E34-K34 | N34: =IF(L34>0, M34/L34, 999)
A35: 33 | B35: =M34 | C35: 0 | D35: =IF(A35<=12, (County_League_Model!B21/12)*(A35/12), IF(A35<=24, (County_League_Model!C21/12), (County_League_Model!D21/12))) | E35: =C35+D35 | F35: =IF(A35<=Summary!C3, (Tranche_Detail!C6)/Summary!C3, IF(A35<=(Summary!C3+Summary!C4), (Tranche_Detail!D6)/Summary!C4, (Tranche_Detail!E6)/Summary!C5)) | G35: =IF(A35<=Summary!C3, (Tranche_Detail!C10)/Summary!C3, IF(A35<=(Summary!C3+Summary!C4), (Tranche_Detail!D10)/Summary!C4, (Tranche_Detail!E10)/Summary!C5)) | H35: =IF(A35<=Summary!C3, (Tranche_Detail!C12)/Summary!C3, IF(A35<=(Summary!C3+Summary!C4), (Tranche_Detail!D12)/Summary!C4, (Tranche_Detail!E12)/Summary!C5)) | I35: =IF(A35<=Summary!C3, (Tranche_Detail!C14)/Summary!C3, IF(A35<=(Summary!C3+Summary!C4), (Tranche_Detail!D14)/Summary!C4, (Tranche_Detail!E14)/Summary!C5)) | J35: =IF(A35<=Summary!C3, (Tranche_Detail!C17)/Summary!C3, IF(A35<=(Summary!C3+Summary!C4), (Tranche_Detail!D17)/Summary!C4, (Tranche_Detail!E17)/Summary!C5)) | K35: =SUM(F35:J35) | L35: =K35-D35 | M35: =B35+E35-K35 | N35: =IF(L35>0, M35/L35, 999)
A36: 34 | B36: =M35 | C36: 0 | D36: =IF(A36<=12, (County_League_Model!B21/12)*(A36/12), IF(A36<=24, (County_League_Model!C21/12), (County_League_Model!D21/12))) | E36: =C36+D36 | F36: =IF(A36<=Summary!C3, (Tranche_Detail!C6)/Summary!C3, IF(A36<=(Summary!C3+Summary!C4), (Tranche_Detail!D6)/Summary!C4, (Tranche_Detail!E6)/Summary!C5)) | G36: =IF(A36<=Summary!C3, (Tranche_Detail!C10)/Summary!C3, IF(A36<=(Summary!C3+Summary!C4), (Tranche_Detail!D10)/Summary!C4, (Tranche_Detail!E10)/Summary!C5)) | H36: =IF(A36<=Summary!C3, (Tranche_Detail!C12)/Summary!C3, IF(A36<=(Summary!C3+Summary!C4), (Tranche_Detail!D12)/Summary!C4, (Tranche_Detail!E12)/Summary!C5)) | I36: =IF(A36<=Summary!C3, (Tranche_Detail!C14)/Summary!C3, IF(A36<=(Summary!C3+Summary!C4), (Tranche_Detail!D14)/Summary!C4, (Tranche_Detail!E14)/Summary!C5)) | J36: =IF(A36<=Summary!C3, (Tranche_Detail!C17)/Summary!C3, IF(A36<=(Summary!C3+Summary!C4), (Tranche_Detail!D17)/Summary!C4, (Tranche_Detail!E17)/Summary!C5)) | K36: =SUM(F36:J36) | L36: =K36-D36 | M36: =B36+E36-K36 | N36: =IF(L36>0, M36/L36, 999)
A37: 35 | B37: =M36 | C37: 0 | D37: =IF(A37<=12, (County_League_Model!B21/12)*(A37/12), IF(A37<=24, (County_League_Model!C21/12), (County_League_Model!D21/12))) | E37: =C37+D37 | F37: =IF(A37<=Summary!C3, (Tranche_Detail!C6)/Summary!C3, IF(A37<=(Summary!C3+Summary!C4), (Tranche_Detail!D6)/Summary!C4, (Tranche_Detail!E6)/Summary!C5)) | G37: =IF(A37<=Summary!C3, (Tranche_Detail!C10)/Summary!C3, IF(A37<=(Summary!C3+Summary!C4), (Tranche_Detail!D10)/Summary!C4, (Tranche_Detail!E10)/Summary!C5)) | H37: =IF(A37<=Summary!C3, (Tranche_Detail!C12)/Summary!C3, IF(A37<=(Summary!C3+Summary!C4), (Tranche_Detail!D12)/Summary!C4, (Tranche_Detail!E12)/Summary!C5)) | I37: =IF(A37<=Summary!C3, (Tranche_Detail!C14)/Summary!C3, IF(A37<=(Summary!C3+Summary!C4), (Tranche_Detail!D14)/Summary!C4, (Tranche_Detail!E14)/Summary!C5)) | J37: =IF(A37<=Summary!C3, (Tranche_Detail!C17)/Summary!C3, IF(A37<=(Summary!C3+Summary!C4), (Tranche_Detail!D17)/Summary!C4, (Tranche_Detail!E17)/Summary!C5)) | K37: =SUM(F37:J37) | L37: =K37-D37 | M37: =B37+E37-K37 | N37: =IF(L37>0, M37/L37, 999)
A38: 36 | B38: =M37 | C38: 0 | D38: =IF(A38<=12, (County_League_Model!B21/12)*(A38/12), IF(A38<=24, (County_League_Model!C21/12), (County_League_Model!D21/12))) | E38: =C38+D38 | F38: =IF(A38<=Summary!C3, (Tranche_Detail!C6)/Summary!C3, IF(A38<=(Summary!C3+Summary!C4), (Tranche_Detail!D6)/Summary!C4, (Tranche_Detail!E6)/Summary!C5)) | G38: =IF(A38<=Summary!C3, (Tranche_Detail!C10)/Summary!C3, IF(A38<=(Summary!C3+Summary!C4), (Tranche_Detail!D10)/Summary!C4, (Tranche_Detail!E10)/Summary!C5)) | H38: =IF(A38<=Summary!C3, (Tranche_Detail!C12)/Summary!C3, IF(A38<=(Summary!C3+Summary!C4), (Tranche_Detail!D12)/Summary!C4, (Tranche_Detail!E12)/Summary!C5)) | I38: =IF(A38<=Summary!C3, (Tranche_Detail!C14)/Summary!C3, IF(A38<=(Summary!C3+Summary!C4), (Tranche_Detail!D14)/Summary!C4, (Tranche_Detail!E14)/Summary!C5)) | J38: =IF(A38<=Summary!C3, (Tranche_Detail!C17)/Summary!C3, IF(A38<=(Summary!C3+Summary!C4), (Tranche_Detail!D17)/Summary!C4, (Tranche_Detail!E17)/Summary!C5)) | K38: =SUM(F38:J38) | L38: =K38-D38 | M38: =B38+E38-K38 | N38: =IF(L38>0, M38/L38, 999)

Sheet Pay_Triggers
A1: Founder Pay Triggers
A2: Stage | B2: Annual Salary (per Founder) | C2: MRR Trigger | D2: Tranche Trigger | E2: Notes
A3: 1 | B3: =Assumptions!C22 | C3: 0 | D3: Tranche A | E3: MVP & Pilot Phase
A4: 2 | B4: =Assumptions!C23 | C4: =Assumptions!C25 | D4: Tranche B | E4: PMF Phase
A5: 3 | B5: =Assumptions!C24 | C5: =Assumptions!C26 | D5: Tranche C | E5: Scale Phase
A7: Current Status
A8: Current MRR | B8: =County_League_Model!D22
A9: Current Annual Pay (per) | B9: =IF(B8>=C4, B4, IF(B8>=C3, B3, B2))
A10: Total Founder Payroll (Annual) | B10: =B9*2

Sheet Milestones
A1: Milestones & KPIs
A2: Tranche | B2: Milestone | C2: Metric | D2: Target | E2: Current | F2: Status
A3: A | B3: MVP Launch | C3: App Live | D3: 1 | E3: 1 | F3: =IF(E3>=D3,"Met","Pending")
A4: A | B4: Umpires Onboarded | C4: Users | D4: 100 | E4: 0 | F4: =IF(E4>=D4,"Met","Pending")
A5: A | B5: Pilot Leagues Secured | C5: Leagues | D5: 5 | E5: =County_League_Model!B5 | F5: =IF(E5>=D5,"Met","Pending")
A6: B | B6: Tranche A Milestones Met | C6: Status | D6: 1 | E6: =IF(F5="Met",1,0) | F6: =IF(E6>=D6,"Met","Pending")
A7: B | B7: Achieve $15k MRR | C7: MRR | D7: 15000 | E7: =County_League_Model!D22 | F7: =IF(E7>=D7,"Met","Pending")
A8: B | B8: Parent Conversion | C8: % | D8: =Assumptions!C8 | E8: =Assumptions!C8 | F8: =IF(E8>=D8,"Met","Pending")
A9: B | B9: Coach Conversion | C9: % | D9: =Assumptions!C9 | E9: =Assumptions!C9 | F9: =IF(E9>=D9,"Met","Pending")
A10: C | B10: Tranche B Milestones Met | C10: Status | D10: 1 | E10: =IF(AND(F7="Met",F8="Met",F9="Met"),1,0) | F10: =IF(E10>=D10,"Met","Pending")
A11: C | B11: Achieve $100k MRR | C11: MRR | D11: 100000 | E11: =County_League_Model!D22 | F11: =IF(E11>=D11,"Met","Pending")
A12: C | B12: Org Contracts | C12: Count | D12: 10 | E12: =County_League_Model!D15 | F12: =IF(E12>=D12,"Met","Pending")

Sheet Scenarios
A1: Scenario Assumptions
A2: Variable | B2: Conservative | C2: Base | D2: Aggressive
A3: Parent Conversion % | B3: =Assumptions!D8 | C3: =Assumptions!C8 | D3: =Assumptions!E8
A4: Coach Conversion % | B4: =Assumptions!D9 | C4: =Assumptions!C9 | D4: =Assumptions!E9
A5: Org Conversion % | B5: =Assumptions!D10 | C5: =Assumptions!C10 | D5: =Assumptions!E10
A6: Org Price (Annual Avg) | B6: =Assumptions!D12 | C6: =Assumptions!C12 | D6: =Assumptions!E12
A7: CAC - Ambassador | B7: =Assumptions!D17 | C7: =Assumptions!C17 | D7: =Assumptions!E17
A8: CAC - Social/Digital | B8: =Assumptions!D18 | C8: =Assumptions!C18 | D8: =Assumptions!E18
A9: CAC - Organization | B9: =Assumptions!D19 | C9: =Assumptions!C19 | D9: =Assumptions!E19

Sheet Scenarios_Output
A1: Scenarios Output Summary
A2: Metric | B2: Conservative | C2: Base | D2: Aggressive
A3: Year 3 ARR | B3: =(County_League_Model!D9*Scenarios!B3*Assumptions!D11) + (County_League_Model!D10*Scenarios!B4*Assumptions!D11) + (County_League_Model!D15*Scenarios!B6) | C3: =County_League_Model!D21 | D3: =(County_League_Model!D9*Scenarios!D3*Assumptions!E11) + (County_League_Model!D10*Scenarios!D4*Assumptions!E11) + (County_League_Model!D15*Scenarios!D6)
A4: Year 3 Total Paid Users | B4: =(County_League_Model!D9*Scenarios!B3) + (County_League_Model!D10*Scenarios!B4) + (County_League_Model!D15) | C4: =County_League_Model!D13 + County_League_Model!D14 + County_League_Model!D15 | D4: =(County_League_Model!D9*Scenarios!D3) + (County_League_Model!D10*Scenarios!D4) + (County_League_Model!D15)
A5: Blended LTV (Year 3) | B5: =(B3/B4) * Assumptions!D14 * Assumptions!D13 | C5: =Unit_Economics!E7 | D5: =(D3/D4) * Assumptions!E14 * Assumptions!E13
A6: Blended Payback (Months) - Est. | B6: ( (Scenarios!B7*B4) + (Scenarios!B9*County_League_Model!D15) ) / (B3*Assumptions!D14) * 12 | C6: =Unit_Economics!E11 | D6: ( (Scenarios!D7*D4) + (Scenarios!D9*County_League_Model!D15) ) / (D3*Assumptions!E14) * 12

Sheet Sales_Comp
A1: Sales Comp Model (Example)
A2: Role | B2: Base Salary | C2: Commission Rate | D2: Bonus Target | E2: Notes / Triggers
A3: Org Sales Rep (Tranche B) | B3: =Assumptions!C21 | C3: 0.1 | D3: 20000 | E3: 10% of 1st Year ACV. Bonus on 100% quota.
A4: Partner Manager (Tranche C) | B4: 90000 | C4: 0.05 | D4: 15000 | E4: 5% of ACV from league partners.
A5: Head of Sales (Tranche C) | B5: 140000 | C5: 0.02 | D5: 50000 | E5: 2% team override. Bonus on team quota.

Sheet Infra_Estimates
A1: Infrastructure Cost Estimates
A2: Item | B2: Cost Driver | C2: Cost per Unit | D2: Units (Year 2) | E2: Total Annual Cost | F2: Notes
A3: Umpire Onboarding/Training | B3: Per Umpire | C3: 10 | D3: =County_League_Model!C8 | E3: =C3*D3 | F3: Manuals, support, background check subsidy
A4: Audio Data Storage (Cloud) | B4: Per Game (Avg) | C4: 0.5 | D4: =(County_League_Model!C8*20) | E4: =C4*D4 | F4: Assuming 20 games/umpire/year
A5: Data Processing (AI) | B5: Per Game (Avg) | C5: 1 | D5: =D4 | E5: =C5*D5 | F5: Analytics & transcription costs
A6: Total Annual Infra COGS | E6: =SUM(E3:E5)
A8: Adjusted Gross Margin
A9: Base Gross Margin | B9: =Assumptions!C15
A10: Infra COGS as % of Revenue (Y2) | B10: =E6/County_League_Model!C21
A11: Adjusted Gross Margin | B11: =B9-B10
